oops_amqp/__init__.py
oops_amqp/anybson.py
oops_amqp/publisher.py
oops_amqp/receiver.py
oops_amqp/trace.py
oops_amqp/utils.py
oops_amqp-0.3.0.dist-info/licenses/LICENSE
oops_amqp-0.3.0.dist-info/METADATA
oops_amqp-0.3.0.dist-info/WHEEL
oops_amqp-0.3.0.dist-info/entry_points.txt
oops_amqp-0.3.0.dist-info/top_level.txt
oops_amqp-0.3.0.dist-info/RECORD
