Metadata-Version: 2.4
Name: oops_amqp
Version: 0.3.0
Summary: OOPS AMQP transport.
Home-page: https://launchpad.net/python-oops-amqp
Maintainer: Launchpad Developers
Maintainer-email: launchpad-dev@lists.launchpad.net
License: LGPL-3.0
Classifier: Development Status :: 2 - Pre-Alpha
Classifier: Intended Audience :: Developers
Classifier: License :: OSI Approved :: GNU Lesser General Public License v3 (LGPLv3)
Classifier: License :: OSI Approved :: GNU Library or Lesser General Public License (LGPL)
Classifier: Operating System :: OS Independent
Classifier: Programming Language :: Python
Classifier: Programming Language :: Python :: 3
Classifier: Programming Language :: Python :: 3.8
License-File: LICENSE
Requires-Dist: amqp>=2.0.0
Requires-Dist: bson
Requires-Dist: oops>=0.1.0
Requires-Dist: kombu
Provides-Extra: test
Requires-Dist: pytest; extra == "test"
Requires-Dist: rabbitfixture; extra == "test"
Dynamic: license-file
